stan_circular_inference/__init__.py
stan_circular_inference/examples/__init__.py
stan_circular_inference/examples/ch1.py
stan_circular_inference/examples/stan_example.py
stan_circular_inference/examples/vonmises_model.py
stan_circular_inference/examples/wind_dataset.py
stan_circular_inference/factories/__init__.py
stan_circular_inference/factories/distributions_factory.py
stan_circular_inference/factories/model_factory.py
stan_circular_inference/factories/parameters_factory.py
stan_circular_inference/factories/vonmises_factory.py
stan_circular_inference/utils/__init__.py
stan_circular_inference/utils/utils.py
stan_circular_inference-0.0.1a6.dist-info/licenses/LICENSE.txt
stan_circular_inference-0.0.1a6.dist-info/METADATA
stan_circular_inference-0.0.1a6.dist-info/WHEEL
stan_circular_inference-0.0.1a6.dist-info/top_level.txt
stan_circular_inference-0.0.1a6.dist-info/RECORD
